{
    "+45+006": [
        {
            "name": "LFHZ",
            "p1": [
                10747.067042039049,
                50311.78691618304
            ],
            "p2": [
                10898.083402762702,
                49658.390736530186
            ],
            "points": [
                [
                    0.0,
                    529.3
                ],
                [
                    100.0,
                    534.1
                ]
            ],
            "width": "72",
            "trans_side": "100"
        }
    ]
}